{
  "query": "SELECT c.id, c.consumptionDate, p.name as productName, c.quantity \nFROM consumption c \nJOIN products p ON c.productId = p.id \nORDER BY c.consumptionDate, p.name;",
  "command": "mysql --batch --raw --column-names --default-character-set=utf8mb4 --host gateway02.us-east-1.prod.aws.tidbcloud.com --port 4000 --user 4FysZ9MrVV6QjYg.root --database EyQJop6MbQkDXkB9byGYLR --execute SELECT c.id, c.consumptionDate, p.name as productName, c.quantity \nFROM consumption c \nJOIN products p ON c.productId = p.id \nORDER BY c.consumptionDate, p.name;",
  "rows": [
    {
      "id": "120001",
      "consumptionDate": "2025-10-28 00:00:00",
      "productName": "Handelsgold Blond",
      "quantity": "2.00"
    },
    {
      "id": "120002",
      "consumptionDate": "2025-10-28 00:00:00",
      "productName": "Handelsgold Blue",
      "quantity": "1.00"
    },
    {
      "id": "120003",
      "consumptionDate": "2025-10-28 00:00:00",
      "productName": "Handelsgold Red",
      "quantity": "2.00"
    },
    {
      "id": "120004",
      "consumptionDate": "2025-10-28 00:00:00",
      "productName": "Panetelas",
      "quantity": "2.00"
    },
    {
      "id": "120009",
      "consumptionDate": "2025-10-28 20:00:00",
      "productName": "Handelsgold Blue",
      "quantity": "1.00"
    },
    {
      "id": "120010",
      "consumptionDate": "2025-10-28 21:00:00",
      "productName": "Panetelas",
      "quantity": "1.00"
    },
    {
      "id": "120011",
      "consumptionDate": "2025-10-28 22:00:00",
      "productName": "Handelsgold Red",
      "quantity": "1.00"
    },
    {
      "id": "120012",
      "consumptionDate": "2025-10-29 09:49:00",
      "productName": "Handelsgold Blond",
      "quantity": "1.00"
    },
    {
      "id": "120005",
      "consumptionDate": "2025-10-29 12:25:00",
      "productName": "Handelsgold Blond",
      "quantity": "1.00"
    },
    {
      "id": "120013",
      "consumptionDate": "2025-10-29 13:30:00",
      "productName": "Handelsgold Blond",
      "quantity": "1.00"
    },
    {
      "id": "120014",
      "consumptionDate": "2025-10-29 14:19:00",
      "productName": "Marlboro Crafted 100s",
      "quantity": "1.00"
    },
    {
      "id": "120006",
      "consumptionDate": "2025-10-29 14:50:00",
      "productName": "Handelsgold Blue",
      "quantity": "1.00"
    },
    {
      "id": "120007",
      "consumptionDate": "2025-10-29 16:05:00",
      "productName": "Panetelas",
      "quantity": "1.00"
    },
    {
      "id": "120016",
      "consumptionDate": "2025-10-29 16:15:00",
      "productName": "Marlboro Crafted 100s",
      "quantity": "1.00"
    },
    {
      "id": "120017",
      "consumptionDate": "2025-10-29 17:07:00",
      "productName": "Marlboro Crafted 100s",
      "quantity": "1.00"
    },
    {
      "id": "120008",
      "consumptionDate": "2025-10-29 18:15:00",
      "productName": "Handelsgold Red",
      "quantity": "1.00"
    },
    {
      "id": "120018",
      "consumptionDate": "2025-10-29 19:44:00",
      "productName": "Marlboro Crafted 100s",
      "quantity": "1.00"
    },
    {
      "id": "120019",
      "consumptionDate": "2025-10-29 21:07:00",
      "productName": "Panetelas",
      "quantity": "0.00"
    },
    {
      "id": "120020",
      "consumptionDate": "2025-10-29 22:00:00",
      "productName": "Handelsgold Blue",
      "quantity": "0.00"
    },
    {
      "id": "120033",
      "consumptionDate": "2025-10-30 00:01:00",
      "productName": "Marlboro Crafted 100s",
      "quantity": "1.00"
    },
    {
      "id": "120021",
      "consumptionDate": "2025-10-30 10:39:00",
      "productName": "Marlboro Crafted 100s",
      "quantity": "1.00"
    },
    {
      "id": "120022",
      "consumptionDate": "2025-10-30 11:31:00",
      "productName": "Marlboro Crafted 100s",
      "quantity": "1.00"
    },
    {
      "id": "120023",
      "consumptionDate": "2025-10-30 12:13:00",
      "productName": "Marlboro Crafted 100s",
      "quantity": "1.00"
    },
    {
      "id": "120024",
      "consumptionDate": "2025-10-30 12:48:00",
      "productName": "Marlboro Crafted 100s",
      "quantity": "1.00"
    },
    {
      "id": "120025",
      "consumptionDate": "2025-10-30 13:20:00",
      "productName": "Panetelas",
      "quantity": "1.00"
    },
    {
      "id": "120026",
      "consumptionDate": "2025-10-30 15:09:00",
      "productName": "Handelsgold Blue",
      "quantity": "0.00"
    },
    {
      "id": "120027",
      "consumptionDate": "2025-10-30 17:07:00",
      "productName": "Marlboro Crafted 100s",
      "quantity": "1.00"
    },
    {
      "id": "120028",
      "consumptionDate": "2025-10-30 18:00:00",
      "productName": "Panetelas",
      "quantity": "0.00"
    },
    {
      "id": "120029",
      "consumptionDate": "2025-10-30 19:34:00",
      "productName": "Marlboro Crafted 100s",
      "quantity": "1.00"
    },
    {
      "id": "120030",
      "consumptionDate": "2025-10-30 20:27:00",
      "productName": "Marlboro Crafted 100s",
      "quantity": "1.00"
    },
    {
      "id": "120031",
      "consumptionDate": "2025-10-30 21:24:00",
      "productName": "Handelsgold Blond",
      "quantity": "0.00"
    },
    {
      "id": "120032",
      "consumptionDate": "2025-10-30 22:39:00",
      "productName": "Handelsgold Blond",
      "quantity": "0.00"
    },
    {
      "id": "120034",
      "consumptionDate": "2025-10-31 01:10:00",
      "productName": "Marlboro Crafted 100s",
      "quantity": "1.00"
    },
    {
      "id": "120035",
      "consumptionDate": "2025-10-31 12:33:00",
      "productName": "Marlboro Crafted 100s",
      "quantity": "1.00"
    },
    {
      "id": "120037",
      "consumptionDate": "2025-10-31 13:12:00",
      "productName": "Marlboro Crafted 100s",
      "quantity": "1.00"
    },
    {
      "id": "120036",
      "consumptionDate": "2025-10-31 13:14:00",
      "productName": "Handelsgold Blue",
      "quantity": "0.00"
    },
    {
      "id": "120038",
      "consumptionDate": "2025-10-31 17:34:00",
      "productName": "Handelsgold Blue",
      "quantity": "0.00"
    },
    {
      "id": "120039",
      "consumptionDate": "2025-10-31 18:53:00",
      "productName": "Marlboro Crafted 100s",
      "quantity": "1.00"
    },
    {
      "id": "120040",
      "consumptionDate": "2025-10-31 20:00:00",
      "productName": "Panetelas",
      "quantity": "0.00"
    },
    {
      "id": "120041",
      "consumptionDate": "2025-10-31 21:00:00",
      "productName": "Marlboro Crafted 100s",
      "quantity": "1.00"
    },
    {
      "id": "120042",
      "consumptionDate": "2025-10-31 21:06:00",
      "productName": "Panetelas",
      "quantity": "0.00"
    },
    {
      "id": "120043",
      "consumptionDate": "2025-10-31 22:55:00",
      "productName": "Marlboro Crafted 100s",
      "quantity": "1.00"
    },
    {
      "id": "120044",
      "consumptionDate": "2025-11-01 12:21:00",
      "productName": "Marlboro Crafted 100s",
      "quantity": "1.00"
    },
    {
      "id": "120045",
      "consumptionDate": "2025-11-01 13:20:00",
      "productName": "Marlboro Crafted 100s",
      "quantity": "1.00"
    },
    {
      "id": "120046",
      "consumptionDate": "2025-11-01 14:28:00",
      "productName": "Marlboro Crafted 100s",
      "quantity": "1.00"
    },
    {
      "id": "120047",
      "consumptionDate": "2025-11-01 15:48:00",
      "productName": "Marlboro Crafted 100s",
      "quantity": "1.00"
    },
    {
      "id": "120048",
      "consumptionDate": "2025-11-01 17:11:00",
      "productName": "Marlboro Crafted 100s",
      "quantity": "1.00"
    },
    {
      "id": "120049",
      "consumptionDate": "2025-11-01 18:11:00",
      "productName": "Marlboro Crafted 100s",
      "quantity": "1.00"
    },
    {
      "id": "120050",
      "consumptionDate": "2025-11-01 19:25:00",
      "productName": "Marlboro Crafted 100s",
      "quantity": "1.00"
    },
    {
      "id": "120051",
      "consumptionDate": "2025-11-01 20:52:00",
      "productName": "Marlboro Crafted 100s",
      "quantity": "1.00"
    },
    {
      "id": "120052",
      "consumptionDate": "2025-11-01 22:02:00",
      "productName": "Handelsgold Blond",
      "quantity": "1.00"
    },
    {
      "id": "120053",
      "consumptionDate": "2025-11-02 00:07:00",
      "productName": "Marlboro Crafted 100s",
      "quantity": "1.00"
    },
    {
      "id": "120054",
      "consumptionDate": "2025-11-02 05:24:00",
      "productName": "Marlboro Crafted 100s",
      "quantity": "1.00"
    },
    {
      "id": "120055",
      "consumptionDate": "2025-11-02 06:49:00",
      "productName": "Marlboro Crafted 100s",
      "quantity": "1.00"
    },
    {
      "id": "120056",
      "consumptionDate": "2025-11-02 08:05:00",
      "productName": "Marlboro Crafted 100s",
      "quantity": "1.00"
    },
    {
      "id": "120057",
      "consumptionDate": "2025-11-02 09:16:00",
      "productName": "Panetelas",
      "quantity": "1.00"
    },
    {
      "id": "120058",
      "consumptionDate": "2025-11-02 10:05:00",
      "productName": "Marlboro Crafted 100s",
      "quantity": "1.00"
    },
    {
      "id": "120059",
      "consumptionDate": "2025-11-02 11:16:00",
      "productName": "Marlboro Crafted 100s",
      "quantity": "0.00"
    },
    {
      "id": "120060",
      "consumptionDate": "2025-11-02 12:54:00",
      "productName": "Marlboro Crafted 100s",
      "quantity": "1.00"
    },
    {
      "id": "120061",
      "consumptionDate": "2025-11-02 14:40:00",
      "productName": "Marlboro Crafted 100s",
      "quantity": "1.00"
    },
    {
      "id": "120062",
      "consumptionDate": "2025-11-02 15:48:00",
      "productName": "Handelsgold Blue",
      "quantity": "0.00"
    },
    {
      "id": "120063",
      "consumptionDate": "2025-11-02 17:18:00",
      "productName": "Marlboro Crafted 100s",
      "quantity": "1.00"
    },
    {
      "id": "120064",
      "consumptionDate": "2025-11-02 18:19:00",
      "productName": "Handelsgold Blue",
      "quantity": "0.00"
    },
    {
      "id": "120065",
      "consumptionDate": "2025-11-02 19:37:00",
      "productName": "Marlboro Crafted 100s",
      "quantity": "1.00"
    },
    {
      "id": "120066",
      "consumptionDate": "2025-11-02 21:26:00",
      "productName": "Marlboro Crafted 100s",
      "quantity": "1.00"
    },
    {
      "id": "120067",
      "consumptionDate": "2025-11-03 12:19:00",
      "productName": "Marlboro Crafted 100s",
      "quantity": "1.00"
    },
    {
      "id": "120068",
      "consumptionDate": "2025-11-03 12:48:00",
      "productName": "Handelsgold Blond",
      "quantity": "1.00"
    },
    {
      "id": "120069",
      "consumptionDate": "2025-11-03 13:47:00",
      "productName": "Marlboro Crafted 100s",
      "quantity": "1.00"
    },
    {
      "id": "120070",
      "consumptionDate": "2025-11-03 15:07:00",
      "productName": "Panetelas",
      "quantity": "1.00"
    },
    {
      "id": "120071",
      "consumptionDate": "2025-11-03 17:56:00",
      "productName": "Marlboro Crafted 100s",
      "quantity": "1.00"
    },
    {
      "id": "120072",
      "consumptionDate": "2025-11-03 19:39:00",
      "productName": "Marlboro Crafted 100s",
      "quantity": "1.00"
    },
    {
      "id": "120073",
      "consumptionDate": "2025-11-03 20:33:00",
      "productName": "Marlboro Crafted 100s",
      "quantity": "1.00"
    },
    {
      "id": "120074",
      "consumptionDate": "2025-11-03 21:46:00",
      "productName": "Marlboro Crafted 100s",
      "quantity": "1.00"
    },
    {
      "id": "120075",
      "consumptionDate": "2025-11-03 22:28:00",
      "productName": "Handelsgold Blue",
      "quantity": "0.00"
    },
    {
      "id": "120076",
      "consumptionDate": "2025-11-04 08:35:00",
      "productName": "Marlboro Crafted 100s",
      "quantity": "1.00"
    },
    {
      "id": "120077",
      "consumptionDate": "2025-11-04 10:03:00",
      "productName": "Handelsgold Blue",
      "quantity": "0.00"
    },
    {
      "id": "120078",
      "consumptionDate": "2025-11-04 10:38:00",
      "productName": "Marlboro Crafted 100s",
      "quantity": "1.00"
    },
    {
      "id": "120079",
      "consumptionDate": "2025-11-04 12:07:00",
      "productName": "Marlboro Crafted 100s",
      "quantity": "1.00"
    },
    {
      "id": "120080",
      "consumptionDate": "2025-11-04 13:10:00",
      "productName": "Handelsgold Blue",
      "quantity": "1.00"
    },
    {
      "id": "120081",
      "consumptionDate": "2025-11-04 14:59:00",
      "productName": "Marlboro Crafted 100s",
      "quantity": "1.00"
    },
    {
      "id": "120082",
      "consumptionDate": "2025-11-04 16:20:00",
      "productName": "Marlboro Crafted 100s",
      "quantity": "0.00"
    },
    {
      "id": "120083",
      "consumptionDate": "2025-11-04 16:55:00",
      "productName": "Marlboro Crafted 100s",
      "quantity": "0.00"
    },
    {
      "id": "120084",
      "consumptionDate": "2025-11-04 17:07:00",
      "productName": "Marlboro Crafted 100s",
      "quantity": "0.00"
    },
    {
      "id": "120085",
      "consumptionDate": "2025-11-04 18:19:00",
      "productName": "Marlboro Crafted 100s",
      "quantity": "0.00"
    },
    {
      "id": "120086",
      "consumptionDate": "2025-11-04 18:54:00",
      "productName": "Panetelas",
      "quantity": "1.00"
    },
    {
      "id": "120087",
      "consumptionDate": "2025-11-04 20:26:00",
      "productName": "Marlboro Crafted 100s",
      "quantity": "0.00"
    },
    {
      "id": "120088",
      "consumptionDate": "2025-11-04 21:30:00",
      "productName": "Marlboro Crafted 100s",
      "quantity": "0.00"
    },
    {
      "id": "120089",
      "consumptionDate": "2025-11-04 22:02:00",
      "productName": "Marlboro Crafted 100s",
      "quantity": "1.00"
    },
    {
      "id": "120090",
      "consumptionDate": "2025-11-05 12:03:00",
      "productName": "Marlboro Crafted 100s",
      "quantity": "1.00"
    },
    {
      "id": "120091",
      "consumptionDate": "2025-11-05 12:46:00",
      "productName": "Marlboro Crafted 100s",
      "quantity": "1.00"
    },
    {
      "id": "120092",
      "consumptionDate": "2025-11-05 15:01:00",
      "productName": "Marlboro Crafted 100s",
      "quantity": "1.00"
    },
    {
      "id": "120093",
      "consumptionDate": "2025-11-05 16:02:00",
      "productName": "Marlboro Crafted 100s",
      "quantity": "1.00"
    },
    {
      "id": "120094",
      "consumptionDate": "2025-11-05 16:55:00",
      "productName": "Panetelas",
      "quantity": "1.00"
    },
    {
      "id": "120095",
      "consumptionDate": "2025-11-05 18:43:00",
      "productName": "Marlboro Crafted 100s",
      "quantity": "1.00"
    },
    {
      "id": "120096",
      "consumptionDate": "2025-11-05 19:41:00",
      "productName": "Panetelas",
      "quantity": "0.00"
    },
    {
      "id": "120097",
      "consumptionDate": "2025-11-05 20:19:00",
      "productName": "Panetelas",
      "quantity": "0.00"
    },
    {
      "id": "120098",
      "consumptionDate": "2025-11-05 21:41:00",
      "productName": "Marlboro Crafted 100s",
      "quantity": "1.00"
    },
    {
      "id": "120102",
      "consumptionDate": "2025-11-06 00:28:00",
      "productName": "Marlboro Crafted 100s",
      "quantity": "0.00"
    },
    {
      "id": "120099",
      "consumptionDate": "2025-11-06 08:51:00",
      "productName": "Marlboro Crafted 100s",
      "quantity": "1.00"
    },
    {
      "id": "120100",
      "consumptionDate": "2025-11-06 09:45:00",
      "productName": "Marlboro Crafted 100s",
      "quantity": "0.00"
    },
    {
      "id": "120101",
      "consumptionDate": "2025-11-06 09:45:00",
      "productName": "Panetelas",
      "quantity": "0.00"
    },
    {
      "id": "120103",
      "consumptionDate": "2025-11-06 13:30:00",
      "productName": "Panetelas",
      "quantity": "0.00"
    },
    {
      "id": "120104",
      "consumptionDate": "2025-11-06 13:53:00",
      "productName": "Marlboro Crafted 100s",
      "quantity": "0.00"
    },
    {
      "id": "120105",
      "consumptionDate": "2025-11-06 13:53:00",
      "productName": "Panetelas",
      "quantity": "0.00"
    },
    {
      "id": "120106",
      "consumptionDate": "2025-11-06 14:55:00",
      "productName": "Marlboro Crafted 100s",
      "quantity": "0.00"
    },
    {
      "id": "120107",
      "consumptionDate": "2025-11-06 15:32:00",
      "productName": "Marlboro Crafted 100s",
      "quantity": "0.00"
    },
    {
      "id": "120109",
      "consumptionDate": "2025-11-06 16:03:00",
      "productName": "Nicaragua Short Puritos",
      "quantity": "1.00"
    },
    {
      "id": "120110",
      "consumptionDate": "2025-11-06 16:45:00",
      "productName": "Reserve 10th Anniversary Puritos",
      "quantity": "1.00"
    },
    {
      "id": "330001",
      "consumptionDate": "2025-11-07 00:00:00",
      "productName": "Brobergs Arcadia",
      "quantity": "1.00"
    },
    {
      "id": "330002",
      "consumptionDate": "2025-11-07 00:00:00",
      "productName": "Brobergs Arcadia",
      "quantity": "1.00"
    },
    {
      "id": "330003",
      "consumptionDate": "2025-11-07 00:00:00",
      "productName": "Brobergs Arcadia",
      "quantity": "1.00"
    },
    {
      "id": "120127",
      "consumptionDate": "2025-11-07 00:55:00",
      "productName": "Marlboro Crafted 100s",
      "quantity": "1.00"
    },
    {
      "id": "120128",
      "consumptionDate": "2025-11-07 02:33:00",
      "productName": "Marlboro Crafted 100s",
      "quantity": "1.00"
    },
    {
      "id": "120113",
      "consumptionDate": "2025-11-07 11:41:00",
      "productName": "Marlboro Crafted 100s",
      "quantity": "0.00"
    },
    {
      "id": "120115",
      "consumptionDate": "2025-11-07 12:00:00",
      "productName": "Marlboro Crafted 100s",
      "quantity": "0.00"
    },
    {
      "id": "120116",
      "consumptionDate": "2025-11-07 12:54:00",
      "productName": "Nicaragua Short Puritos",
      "quantity": "1.00"
    },
    {
      "id": "120118",
      "consumptionDate": "2025-11-07 14:22:00",
      "productName": "Marlboro Crafted 100s",
      "quantity": "1.00"
    },
    {
      "id": "120119",
      "consumptionDate": "2025-11-07 15:33:00",
      "productName": "Marlboro Crafted 100s",
      "quantity": "0.00"
    },
    {
      "id": "120121",
      "consumptionDate": "2025-11-07 16:34:00",
      "productName": "Marlboro Crafted 100s",
      "quantity": "1.00"
    },
    {
      "id": "120122",
      "consumptionDate": "2025-11-07 17:26:00",
      "productName": "Marlboro Crafted 100s",
      "quantity": "1.00"
    },
    {
      "id": "120123",
      "consumptionDate": "2025-11-07 18:15:00",
      "productName": "Nicaragua Short Puritos",
      "quantity": "0.00"
    },
    {
      "id": "120124",
      "consumptionDate": "2025-11-07 19:31:00",
      "productName": "Nicaragua Short Puritos",
      "quantity": "0.00"
    },
    {
      "id": "120126",
      "consumptionDate": "2025-11-07 23:00:00",
      "productName": "Marlboro Crafted 100s",
      "quantity": "1.00"
    },
    {
      "id": "330005",
      "consumptionDate": "2025-11-08 00:00:00",
      "productName": "Brobergs Arcadia",
      "quantity": "0.50"
    },
    {
      "id": "330004",
      "consumptionDate": "2025-11-08 00:00:00",
      "productName": "Brobergs Arcadia",
      "quantity": "0.50"
    },
    {
      "id": "330007",
      "consumptionDate": "2025-11-08 00:00:00",
      "productName": "Brobergs Arcadia",
      "quantity": "1.00"
    },
    {
      "id": "330006",
      "consumptionDate": "2025-11-08 00:00:00",
      "productName": "Brobergs Arcadia",
      "quantity": "1.00"
    },
    {
      "id": "120129",
      "consumptionDate": "2025-11-08 12:29:00",
      "productName": "Marlboro Crafted 100s",
      "quantity": "1.00"
    },
    {
      "id": "120130",
      "consumptionDate": "2025-11-08 15:30:00",
      "productName": "Marlboro Crafted 100s",
      "quantity": "0.00"
    },
    {
      "id": "120133",
      "consumptionDate": "2025-11-08 18:04:00",
      "productName": "Marlboro Crafted 100s",
      "quantity": "0.00"
    },
    {
      "id": "120134",
      "consumptionDate": "2025-11-08 18:52:00",
      "productName": "Marlboro Crafted 100s",
      "quantity": "0.00"
    },
    {
      "id": "120135",
      "consumptionDate": "2025-11-08 20:10:00",
      "productName": "Marlboro Crafted 100s",
      "quantity": "0.00"
    },
    {
      "id": "120136",
      "consumptionDate": "2025-11-08 22:00:00",
      "productName": "Marlboro Crafted 100s",
      "quantity": "1.00"
    },
    {
      "id": "330009",
      "consumptionDate": "2025-11-09 00:00:00",
      "productName": "Brobergs Arcadia",
      "quantity": "0.50"
    },
    {
      "id": "330008",
      "consumptionDate": "2025-11-09 00:00:00",
      "productName": "Brobergs Arcadia",
      "quantity": "0.50"
    },
    {
      "id": "120137",
      "consumptionDate": "2025-11-09 08:35:00",
      "productName": "Marlboro Crafted 100s",
      "quantity": "1.00"
    },
    {
      "id": "120139",
      "consumptionDate": "2025-11-09 10:16:00",
      "productName": "Marlboro Crafted 100s",
      "quantity": "1.00"
    },
    {
      "id": "120140",
      "consumptionDate": "2025-11-09 11:19:00",
      "productName": "Marlboro Crafted 100s",
      "quantity": "1.00"
    },
    {
      "id": "120141",
      "consumptionDate": "2025-11-09 12:00:00",
      "productName": "Marlboro Crafted 100s",
      "quantity": "0.00"
    },
    {
      "id": "120142",
      "consumptionDate": "2025-11-09 12:52:00",
      "productName": "Marlboro Crafted 100s",
      "quantity": "0.00"
    },
    {
      "id": "120143",
      "consumptionDate": "2025-11-09 14:28:00",
      "productName": "Marlboro Crafted 100s",
      "quantity": "1.00"
    },
    {
      "id": "120146",
      "consumptionDate": "2025-11-09 18:00:00",
      "productName": "Marlboro Crafted 100s",
      "quantity": "1.00"
    },
    {
      "id": "120147",
      "consumptionDate": "2025-11-09 19:10:00",
      "productName": "Marlboro Crafted 100s",
      "quantity": "1.00"
    },
    {
      "id": "330011",
      "consumptionDate": "2025-11-10 00:00:00",
      "productName": "Brobergs Arcadia",
      "quantity": "0.80"
    },
    {
      "id": "330010",
      "consumptionDate": "2025-11-10 00:00:00",
      "productName": "Brobergs Arcadia",
      "quantity": "1.00"
    },
    {
      "id": "330012",
      "consumptionDate": "2025-11-10 00:00:00",
      "productName": "Brobergs Arcadia",
      "quantity": "0.20"
    },
    {
      "id": "330013",
      "consumptionDate": "2025-11-10 00:00:00",
      "productName": "Brobergs Arcadia",
      "quantity": "0.70"
    },
    {
      "id": "330014",
      "consumptionDate": "2025-11-10 00:00:00",
      "productName": "Brobergs Arcadia",
      "quantity": "0.10"
    },
    {
      "id": "120152",
      "consumptionDate": "2025-11-10 15:20:00",
      "productName": "Marlboro Crafted 100s",
      "quantity": "0.00"
    },
    {
      "id": "120154",
      "consumptionDate": "2025-11-10 16:22:00",
      "productName": "Marlboro Crafted 100s",
      "quantity": "1.00"
    },
    {
      "id": "120155",
      "consumptionDate": "2025-11-10 17:02:00",
      "productName": "Marlboro Crafted 100s",
      "quantity": "0.00"
    },
    {
      "id": "120156",
      "consumptionDate": "2025-11-10 18:00:00",
      "productName": "Marlboro Crafted 100s",
      "quantity": "0.00"
    },
    {
      "id": "330017",
      "consumptionDate": "2025-11-11 00:00:00",
      "productName": "Brobergs Arcadia",
      "quantity": "0.20"
    },
    {
      "id": "330015",
      "consumptionDate": "2025-11-11 00:00:00",
      "productName": "Brobergs Arcadia",
      "quantity": "0.50"
    },
    {
      "id": "330016",
      "consumptionDate": "2025-11-11 00:00:00",
      "productName": "Brobergs Arcadia",
      "quantity": "0.50"
    },
    {
      "id": "330018",
      "consumptionDate": "2025-11-11 00:00:00",
      "productName": "Brobergs Arcadia",
      "quantity": "0.50"
    },
    {
      "id": "120159",
      "consumptionDate": "2025-11-11 10:05:00",
      "productName": "Marlboro Crafted 100s",
      "quantity": "1.00"
    },
    {
      "id": "120160",
      "consumptionDate": "2025-11-11 12:03:00",
      "productName": "Marlboro Crafted 100s",
      "quantity": "1.00"
    },
    {
      "id": "120161",
      "consumptionDate": "2025-11-11 13:15:00",
      "productName": "Marlboro Crafted 100s",
      "quantity": "1.00"
    },
    {
      "id": "120162",
      "consumptionDate": "2025-11-11 13:55:00",
      "productName": "Marlboro Crafted 100s",
      "quantity": "1.00"
    },
    {
      "id": "330021",
      "consumptionDate": "2025-11-12 00:00:00",
      "productName": "Brobergs Arcadia",
      "quantity": "0.30"
    },
    {
      "id": "330019",
      "consumptionDate": "2025-11-12 00:00:00",
      "productName": "Brobergs Arcadia",
      "quantity": "0.50"
    },
    {
      "id": "330020",
      "consumptionDate": "2025-11-12 00:00:00",
      "productName": "Brobergs Arcadia",
      "quantity": "0.50"
    },
    {
      "id": "330022",
      "consumptionDate": "2025-11-12 00:00:00",
      "productName": "Brobergs Arcadia",
      "quantity": "0.20"
    },
    {
      "id": "330023",
      "consumptionDate": "2025-11-12 00:00:00",
      "productName": "Brobergs Arcadia",
      "quantity": "1.00"
    },
    {
      "id": "120167",
      "consumptionDate": "2025-11-12 08:39:00",
      "productName": "Marlboro Crafted 100s",
      "quantity": "1.00"
    },
    {
      "id": "120168",
      "consumptionDate": "2025-11-12 09:40:00",
      "productName": "Marlboro Crafted 100s",
      "quantity": "1.00"
    },
    {
      "id": "120169",
      "consumptionDate": "2025-11-12 10:09:00",
      "productName": "Marlboro Crafted 100s",
      "quantity": "1.00"
    },
    {
      "id": "330024",
      "consumptionDate": "2025-11-13 00:00:00",
      "productName": "Brobergs Arcadia",
      "quantity": "0.30"
    },
    {
      "id": "330025",
      "consumptionDate": "2025-11-13 00:00:00",
      "productName": "Brobergs Arcadia",
      "quantity": "0.70"
    },
    {
      "id": "120171",
      "consumptionDate": "2025-11-13 10:45:00",
      "productName": "XQS Strawberry Kiwi",
      "quantity": "1.00"
    },
    {
      "id": "120172",
      "consumptionDate": "2025-11-13 13:19:00",
      "productName": "Brobergs Arcadia",
      "quantity": "0.30"
    },
    {
      "id": "150001",
      "consumptionDate": "2025-11-13 14:21:00",
      "productName": "XQS Strawberry Kiwi",
      "quantity": "1.00"
    },
    {
      "id": "180001",
      "consumptionDate": "2025-11-13 16:15:00",
      "productName": "Brobergs Arcadia",
      "quantity": "0.70"
    },
    {
      "id": "210001",
      "consumptionDate": "2025-11-13 18:21:00",
      "productName": "XQS Strawberry Kiwi",
      "quantity": "1.00"
    },
    {
      "id": "330026",
      "consumptionDate": "2025-11-14 00:00:00",
      "productName": "Brobergs Arcadia",
      "quantity": "1.00"
    },
    {
      "id": "210002",
      "consumptionDate": "2025-11-14 08:04:00",
      "productName": "XQS Strawberry Kiwi",
      "quantity": "1.00"
    },
    {
      "id": "240001",
      "consumptionDate": "2025-11-14 08:22:00",
      "productName": "Marlboro Crafted 100s",
      "quantity": "1.00"
    },
    {
      "id": "270001",
      "consumptionDate": "2025-11-14 09:18:00",
      "productName": "Brobergs Arcadia",
      "quantity": "1.00"
    },
    {
      "id": "300001",
      "consumptionDate": "2025-11-14 10:00:00",
      "productName": "XQS Strawberry Kiwi",
      "quantity": "1.00"
    },
    {
      "id": "360001",
      "consumptionDate": "2025-11-14 13:24:00",
      "productName": "Brobergs Arcadia",
      "quantity": "1.00"
    },
    {
      "id": "360002",
      "consumptionDate": "2025-11-14 14:28:00",
      "productName": "XQS Strawberry Kiwi",
      "quantity": "1.00"
    },
    {
      "id": "390001",
      "consumptionDate": "2025-11-14 19:25:00",
      "productName": "XQS Strawberry Kiwi",
      "quantity": "1.00"
    },
    {
      "id": "420001",
      "consumptionDate": "2025-11-15 10:07:00",
      "productName": "XQS Strawberry Kiwi",
      "quantity": "1.00"
    },
    {
      "id": "450001",
      "consumptionDate": "2025-11-15 10:22:00",
      "productName": "Brobergs Arcadia",
      "quantity": "1.00"
    }
  ],
  "messages": [],
  "stdout": "id\tconsumptionDate\tproductName\tquantity\n120001\t2025-10-28 00:00:00\tHandelsgold Blond\t2.00\n120002\t2025-10-28 00:00:00\tHandelsgold Blue\t1.00\n120003\t2025-10-28 00:00:00\tHandelsgold Red\t2.00\n120004\t2025-10-28 00:00:00\tPanetelas\t2.00\n120009\t2025-10-28 20:00:00\tHandelsgold Blue\t1.00\n120010\t2025-10-28 21:00:00\tPanetelas\t1.00\n120011\t2025-10-28 22:00:00\tHandelsgold Red\t1.00\n120012\t2025-10-29 09:49:00\tHandelsgold Blond\t1.00\n120005\t2025-10-29 12:25:00\tHandelsgold Blond\t1.00\n120013\t2025-10-29 13:30:00\tHandelsgold Blond\t1.00\n120014\t2025-10-29 14:19:00\tMarlboro Crafted 100s\t1.00\n120006\t2025-10-29 14:50:00\tHandelsgold Blue\t1.00\n120007\t2025-10-29 16:05:00\tPanetelas\t1.00\n120016\t2025-10-29 16:15:00\tMarlboro Crafted 100s\t1.00\n120017\t2025-10-29 17:07:00\tMarlboro Crafted 100s\t1.00\n120008\t2025-10-29 18:15:00\tHandelsgold Red\t1.00\n120018\t2025-10-29 19:44:00\tMarlboro Crafted 100s\t1.00\n120019\t2025-10-29 21:07:00\tPanetelas\t0.00\n120020\t2025-10-29 22:00:00\tHandelsgold Blue\t0.00\n120033\t2025-10-30 00:01:00\tMarlboro Crafted 100s\t1.00\n120021\t2025-10-30 10:39:00\tMarlboro Crafted 100s\t1.00\n120022\t2025-10-30 11:31:00\tMarlboro Crafted 100s\t1.00\n120023\t2025-10-30 12:13:00\tMarlboro Crafted 100s\t1.00\n120024\t2025-10-30 12:48:00\tMarlboro Crafted 100s\t1.00\n120025\t2025-10-30 13:20:00\tPanetelas\t1.00\n120026\t2025-10-30 15:09:00\tHandelsgold Blue\t0.00\n120027\t2025-10-30 17:07:00\tMarlboro Crafted 100s\t1.00\n120028\t2025-10-30 18:00:00\tPanetelas\t0.00\n120029\t2025-10-30 19:34:00\tMarlboro Crafted 100s\t1.00\n120030\t2025-10-30 20:27:00\tMarlboro Crafted 100s\t1.00\n120031\t2025-10-30 21:24:00\tHandelsgold Blond\t0.00\n120032\t2025-10-30 22:39:00\tHandelsgold Blond\t0.00\n120034\t2025-10-31 01:10:00\tMarlboro Crafted 100s\t1.00\n120035\t2025-10-31 12:33:00\tMarlboro Crafted 100s\t1.00\n120037\t2025-10-31 13:12:00\tMarlboro Crafted 100s\t1.00\n120036\t2025-10-31 13:14:00\tHandelsgold Blue\t0.00\n120038\t2025-10-31 17:34:00\tHandelsgold Blue\t0.00\n120039\t2025-10-31 18:53:00\tMarlboro Crafted 100s\t1.00\n120040\t2025-10-31 20:00:00\tPanetelas\t0.00\n120041\t2025-10-31 21:00:00\tMarlboro Crafted 100s\t1.00\n120042\t2025-10-31 21:06:00\tPanetelas\t0.00\n120043\t2025-10-31 22:55:00\tMarlboro Crafted 100s\t1.00\n120044\t2025-11-01 12:21:00\tMarlboro Crafted 100s\t1.00\n120045\t2025-11-01 13:20:00\tMarlboro Crafted 100s\t1.00\n120046\t2025-11-01 14:28:00\tMarlboro Crafted 100s\t1.00\n120047\t2025-11-01 15:48:00\tMarlboro Crafted 100s\t1.00\n120048\t2025-11-01 17:11:00\tMarlboro Crafted 100s\t1.00\n120049\t2025-11-01 18:11:00\tMarlboro Crafted 100s\t1.00\n120050\t2025-11-01 19:25:00\tMarlboro Crafted 100s\t1.00\n120051\t2025-11-01 20:52:00\tMarlboro Crafted 100s\t1.00\n120052\t2025-11-01 22:02:00\tHandelsgold Blond\t1.00\n120053\t2025-11-02 00:07:00\tMarlboro Crafted 100s\t1.00\n120054\t2025-11-02 05:24:00\tMarlboro Crafted 100s\t1.00\n120055\t2025-11-02 06:49:00\tMarlboro Crafted 100s\t1.00\n120056\t2025-11-02 08:05:00\tMarlboro Crafted 100s\t1.00\n120057\t2025-11-02 09:16:00\tPanetelas\t1.00\n120058\t2025-11-02 10:05:00\tMarlboro Crafted 100s\t1.00\n120059\t2025-11-02 11:16:00\tMarlboro Crafted 100s\t0.00\n120060\t2025-11-02 12:54:00\tMarlboro Crafted 100s\t1.00\n120061\t2025-11-02 14:40:00\tMarlboro Crafted 100s\t1.00\n120062\t2025-11-02 15:48:00\tHandelsgold Blue\t0.00\n120063\t2025-11-02 17:18:00\tMarlboro Crafted 100s\t1.00\n120064\t2025-11-02 18:19:00\tHandelsgold Blue\t0.00\n120065\t2025-11-02 19:37:00\tMarlboro Crafted 100s\t1.00\n120066\t2025-11-02 21:26:00\tMarlboro Crafted 100s\t1.00\n120067\t2025-11-03 12:19:00\tMarlboro Crafted 100s\t1.00\n120068\t2025-11-03 12:48:00\tHandelsgold Blond\t1.00\n120069\t2025-11-03 13:47:00\tMarlboro Crafted 100s\t1.00\n120070\t2025-11-03 15:07:00\tPanetelas\t1.00\n120071\t2025-11-03 17:56:00\tMarlboro Crafted 100s\t1.00\n120072\t2025-11-03 19:39:00\tMarlboro Crafted 100s\t1.00\n120073\t2025-11-03 20:33:00\tMarlboro Crafted 100s\t1.00\n120074\t2025-11-03 21:46:00\tMarlboro Crafted 100s\t1.00\n120075\t2025-11-03 22:28:00\tHandelsgold Blue\t0.00\n120076\t2025-11-04 08:35:00\tMarlboro Crafted 100s\t1.00\n120077\t2025-11-04 10:03:00\tHandelsgold Blue\t0.00\n120078\t2025-11-04 10:38:00\tMarlboro Crafted 100s\t1.00\n120079\t2025-11-04 12:07:00\tMarlboro Crafted 100s\t1.00\n120080\t2025-11-04 13:10:00\tHandelsgold Blue\t1.00\n120081\t2025-11-04 14:59:00\tMarlboro Crafted 100s\t1.00\n120082\t2025-11-04 16:20:00\tMarlboro Crafted 100s\t0.00\n120083\t2025-11-04 16:55:00\tMarlboro Crafted 100s\t0.00\n120084\t2025-11-04 17:07:00\tMarlboro Crafted 100s\t0.00\n120085\t2025-11-04 18:19:00\tMarlboro Crafted 100s\t0.00\n120086\t2025-11-04 18:54:00\tPanetelas\t1.00\n120087\t2025-11-04 20:26:00\tMarlboro Crafted 100s\t0.00\n120088\t2025-11-04 21:30:00\tMarlboro Crafted 100s\t0.00\n120089\t2025-11-04 22:02:00\tMarlboro Crafted 100s\t1.00\n120090\t2025-11-05 12:03:00\tMarlboro Crafted 100s\t1.00\n120091\t2025-11-05 12:46:00\tMarlboro Crafted 100s\t1.00\n120092\t2025-11-05 15:01:00\tMarlboro Crafted 100s\t1.00\n120093\t2025-11-05 16:02:00\tMarlboro Crafted 100s\t1.00\n120094\t2025-11-05 16:55:00\tPanetelas\t1.00\n120095\t2025-11-05 18:43:00\tMarlboro Crafted 100s\t1.00\n120096\t2025-11-05 19:41:00\tPanetelas\t0.00\n120097\t2025-11-05 20:19:00\tPanetelas\t0.00\n120098\t2025-11-05 21:41:00\tMarlboro Crafted 100s\t1.00\n120102\t2025-11-06 00:28:00\tMarlboro Crafted 100s\t0.00\n120099\t2025-11-06 08:51:00\tMarlboro Crafted 100s\t1.00\n120100\t2025-11-06 09:45:00\tMarlboro Crafted 100s\t0.00\n120101\t2025-11-06 09:45:00\tPanetelas\t0.00\n120103\t2025-11-06 13:30:00\tPanetelas\t0.00\n120104\t2025-11-06 13:53:00\tMarlboro Crafted 100s\t0.00\n120105\t2025-11-06 13:53:00\tPanetelas\t0.00\n120106\t2025-11-06 14:55:00\tMarlboro Crafted 100s\t0.00\n120107\t2025-11-06 15:32:00\tMarlboro Crafted 100s\t0.00\n120109\t2025-11-06 16:03:00\tNicaragua Short Puritos\t1.00\n120110\t2025-11-06 16:45:00\tReserve 10th Anniversary Puritos\t1.00\n330001\t2025-11-07 00:00:00\tBrobergs Arcadia\t1.00\n330002\t2025-11-07 00:00:00\tBrobergs Arcadia\t1.00\n330003\t2025-11-07 00:00:00\tBrobergs Arcadia\t1.00\n120127\t2025-11-07 00:55:00\tMarlboro Crafted 100s\t1.00\n120128\t2025-11-07 02:33:00\tMarlboro Crafted 100s\t1.00\n120113\t2025-11-07 11:41:00\tMarlboro Crafted 100s\t0.00\n120115\t2025-11-07 12:00:00\tMarlboro Crafted 100s\t0.00\n120116\t2025-11-07 12:54:00\tNicaragua Short Puritos\t1.00\n120118\t2025-11-07 14:22:00\tMarlboro Crafted 100s\t1.00\n120119\t2025-11-07 15:33:00\tMarlboro Crafted 100s\t0.00\n120121\t2025-11-07 16:34:00\tMarlboro Crafted 100s\t1.00\n120122\t2025-11-07 17:26:00\tMarlboro Crafted 100s\t1.00\n120123\t2025-11-07 18:15:00\tNicaragua Short Puritos\t0.00\n120124\t2025-11-07 19:31:00\tNicaragua Short Puritos\t0.00\n120126\t2025-11-07 23:00:00\tMarlboro Crafted 100s\t1.00\n330005\t2025-11-08 00:00:00\tBrobergs Arcadia\t0.50\n330004\t2025-11-08 00:00:00\tBrobergs Arcadia\t0.50\n330007\t2025-11-08 00:00:00\tBrobergs Arcadia\t1.00\n330006\t2025-11-08 00:00:00\tBrobergs Arcadia\t1.00\n120129\t2025-11-08 12:29:00\tMarlboro Crafted 100s\t1.00\n120130\t2025-11-08 15:30:00\tMarlboro Crafted 100s\t0.00\n120133\t2025-11-08 18:04:00\tMarlboro Crafted 100s\t0.00\n120134\t2025-11-08 18:52:00\tMarlboro Crafted 100s\t0.00\n120135\t2025-11-08 20:10:00\tMarlboro Crafted 100s\t0.00\n120136\t2025-11-08 22:00:00\tMarlboro Crafted 100s\t1.00\n330009\t2025-11-09 00:00:00\tBrobergs Arcadia\t0.50\n330008\t2025-11-09 00:00:00\tBrobergs Arcadia\t0.50\n120137\t2025-11-09 08:35:00\tMarlboro Crafted 100s\t1.00\n120139\t2025-11-09 10:16:00\tMarlboro Crafted 100s\t1.00\n120140\t2025-11-09 11:19:00\tMarlboro Crafted 100s\t1.00\n120141\t2025-11-09 12:00:00\tMarlboro Crafted 100s\t0.00\n120142\t2025-11-09 12:52:00\tMarlboro Crafted 100s\t0.00\n120143\t2025-11-09 14:28:00\tMarlboro Crafted 100s\t1.00\n120146\t2025-11-09 18:00:00\tMarlboro Crafted 100s\t1.00\n120147\t2025-11-09 19:10:00\tMarlboro Crafted 100s\t1.00\n330011\t2025-11-10 00:00:00\tBrobergs Arcadia\t0.80\n330010\t2025-11-10 00:00:00\tBrobergs Arcadia\t1.00\n330012\t2025-11-10 00:00:00\tBrobergs Arcadia\t0.20\n330013\t2025-11-10 00:00:00\tBrobergs Arcadia\t0.70\n330014\t2025-11-10 00:00:00\tBrobergs Arcadia\t0.10\n120152\t2025-11-10 15:20:00\tMarlboro Crafted 100s\t0.00\n120154\t2025-11-10 16:22:00\tMarlboro Crafted 100s\t1.00\n120155\t2025-11-10 17:02:00\tMarlboro Crafted 100s\t0.00\n120156\t2025-11-10 18:00:00\tMarlboro Crafted 100s\t0.00\n330017\t2025-11-11 00:00:00\tBrobergs Arcadia\t0.20\n330015\t2025-11-11 00:00:00\tBrobergs Arcadia\t0.50\n330016\t2025-11-11 00:00:00\tBrobergs Arcadia\t0.50\n330018\t2025-11-11 00:00:00\tBrobergs Arcadia\t0.50\n120159\t2025-11-11 10:05:00\tMarlboro Crafted 100s\t1.00\n120160\t2025-11-11 12:03:00\tMarlboro Crafted 100s\t1.00\n120161\t2025-11-11 13:15:00\tMarlboro Crafted 100s\t1.00\n120162\t2025-11-11 13:55:00\tMarlboro Crafted 100s\t1.00\n330021\t2025-11-12 00:00:00\tBrobergs Arcadia\t0.30\n330019\t2025-11-12 00:00:00\tBrobergs Arcadia\t0.50\n330020\t2025-11-12 00:00:00\tBrobergs Arcadia\t0.50\n330022\t2025-11-12 00:00:00\tBrobergs Arcadia\t0.20\n330023\t2025-11-12 00:00:00\tBrobergs Arcadia\t1.00\n120167\t2025-11-12 08:39:00\tMarlboro Crafted 100s\t1.00\n120168\t2025-11-12 09:40:00\tMarlboro Crafted 100s\t1.00\n120169\t2025-11-12 10:09:00\tMarlboro Crafted 100s\t1.00\n330024\t2025-11-13 00:00:00\tBrobergs Arcadia\t0.30\n330025\t2025-11-13 00:00:00\tBrobergs Arcadia\t0.70\n120171\t2025-11-13 10:45:00\tXQS Strawberry Kiwi\t1.00\n120172\t2025-11-13 13:19:00\tBrobergs Arcadia\t0.30\n150001\t2025-11-13 14:21:00\tXQS Strawberry Kiwi\t1.00\n180001\t2025-11-13 16:15:00\tBrobergs Arcadia\t0.70\n210001\t2025-11-13 18:21:00\tXQS Strawberry Kiwi\t1.00\n330026\t2025-11-14 00:00:00\tBrobergs Arcadia\t1.00\n210002\t2025-11-14 08:04:00\tXQS Strawberry Kiwi\t1.00\n240001\t2025-11-14 08:22:00\tMarlboro Crafted 100s\t1.00\n270001\t2025-11-14 09:18:00\tBrobergs Arcadia\t1.00\n300001\t2025-11-14 10:00:00\tXQS Strawberry Kiwi\t1.00\n360001\t2025-11-14 13:24:00\tBrobergs Arcadia\t1.00\n360002\t2025-11-14 14:28:00\tXQS Strawberry Kiwi\t1.00\n390001\t2025-11-14 19:25:00\tXQS Strawberry Kiwi\t1.00\n420001\t2025-11-15 10:07:00\tXQS Strawberry Kiwi\t1.00\n450001\t2025-11-15 10:22:00\tBrobergs Arcadia\t1.00\n",
  "stderr": "",
  "execution_time_ms": 419
}